{"v":"5.5.9","fr":60,"ip":0,"op":180,"w":512,"h":512,"nm":"Bool_Hi","ddd":0,"assets":[],"layers":[{"ddd":0,"ind":1,"ty":3,"nm":"ШАР","sr":1,"ks":{"o":{"a":0,"k":0,"ix":11},"r":{"a":0,"k":0,"ix":10},"p":{"a":1,"k":[{"i":{"x":0.667,"y":1},"o":{"x":0.333,"y":0},"t":0,"s":[370,320,0],"to":[-0.333,-3.333,0],"ti":[0,0,0]},{"i":{"x":0.667,"y":1},"o":{"x":0.333,"y":0},"t":89,"s":[368,300,0],"to":[0,0,0],"ti":[-0.333,-3.333,0]},{"t":179,"s":[370,320,0]}],"ix":2},"a":{"a":0,"k":[0,0,0],"ix":1},"s":{"a":0,"k":[100,100,100],"ix":6}},"ao":0,"ip":0,"op":180,"st":0,"bm":0},{"ddd":0,"ind":2,"ty":3,"nm":"РОТ","parent":1,"sr":1,"ks":{"o":{"a":0,"k":0,"ix":11},"r":{"a":0,"k":0,"ix":10},"p":{"a":0,"k":[-293,106,0],"ix":2},"a":{"a":0,"k":[50,100,0],"ix":1},"s":{"a":0,"k":[100,100,100],"ix":6}},"ao":0,"ip":0,"op":180,"st":0,"bm":0},{"ddd":0,"ind":3,"ty":3,"nm":"БРОВИ","parent":1,"sr":1,"ks":{"o":{"a":0,"k":0,"ix":11},"r":{"a":0,"k":0,"ix":10},"p":{"a":1,"k":[{"i":{"x":0.667,"y":1},"o":{"x":0.333,"y":0},"t":0,"s":[-346,-286,0],"to":[0,2.667,0],"ti":[0,0,0]},{"i":{"x":0.667,"y":1},"o":{"x":0.333,"y":0},"t":9,"s":[-346,-270,0],"to":[0,0,0],"ti":[0,2.667,0]},{"t":22,"s":[-346,-286,0]}],"ix":2},"a":{"a":0,"k":[0,0,0],"ix":1},"s":{"a":0,"k":[100,100,100],"ix":6}},"ao":0,"ip":0,"op":180,"st":0,"bm":0},{"ddd":0,"ind":4,"ty":3,"nm":"РЕСНИЦА","parent":1,"sr":1,"ks":{"o":{"a":0,"k":0,"ix":11},"r":{"a":0,"k":0,"ix":10},"p":{"a":1,"k":[{"i":{"x":0.667,"y":1},"o":{"x":0.333,"y":0},"t":0,"s":[23,-157,0],"to":[-0.25,11.5,0],"ti":[0,0,0]},{"i":{"x":0.667,"y":1},"o":{"x":0.333,"y":0},"t":10,"s":[21.5,-88,0],"to":[0,0,0],"ti":[-0.25,11.5,0]},{"t":20,"s":[23,-157,0]}],"ix":2},"a":{"a":0,"k":[0,0,0],"ix":1},"s":{"a":1,"k":[{"i":{"x":[0.667,0.667,0.667],"y":[1,1,1]},"o":{"x":[0.333,0.333,0.333],"y":[0,0,0]},"t":0,"s":[91,82,100]},{"i":{"x":[0.667,0.667,0.667],"y":[1,1,1]},"o":{"x":[0.333,0.333,0.333],"y":[0,0,0]},"t":10,"s":[91,28.5,100]},{"t":20,"s":[91,82,100]}],"ix":6}},"ao":0,"ip":0,"op":180,"st":0,"bm":0},{"ddd":0,"ind":5,"ty":3,"nm":"МАСШТАБ","sr":1,"ks":{"o":{"a":0,"k":0,"ix":11},"r":{"a":0,"k":0,"ix":10},"p":{"a":0,"k":[257,260,0],"ix":2},"a":{"a":0,"k":[0,0,0],"ix":1},"s":{"a":0,"k":[130,130,100],"ix":6}},"ao":0,"ip":0,"op":180,"st":0,"bm":0},{"ddd":0,"ind":6,"ty":4,"nm":"Блик на шаре","parent":30,"sr":1,"ks":{"o":{"a":0,"k":100,"ix":11},"r":{"a":1,"k":[{"i":{"x":[0.667],"y":[1]},"o":{"x":[0.333],"y":[0]},"t":0,"s":[0]},{"i":{"x":[0.667],"y":[1]},"o":{"x":[0.333],"y":[0]},"t":106,"s":[-11]},{"t":179,"s":[0]}],"ix":10},"p":{"a":1,"k":[{"i":{"x":0.667,"y":1},"o":{"x":0.333,"y":0},"t":0,"s":[145.398,51.629,0],"to":[-2.333,-2.333,0],"ti":[0,0,0]},{"i":{"x":0.667,"y":1},"o":{"x":0.333,"y":0},"t":91,"s":[131.398,37.629,0],"to":[0,0,0],"ti":[-2.333,-2.333,0]},{"t":179,"s":[145.398,51.629,0]}],"ix":2},"a":{"a":0,"k":[18.182,20.567,0],"ix":1},"s":{"a":0,"k":[100,100,100],"ix":6}},"ao":0,"shapes":[{"ty":"gr","it":[{"ind":0,"ty":"sh","ix":1,"ks":{"a":0,"k":{"i":[[3.171,-4.332],[-2.296,3.478]],"o":[[-2.38,3.251],[2.049,-3.105]],"v":[[3.035,2.283],[-3.91,-2.429]],"c":true},"ix":2},"nm":"Контур 1","mn":"ADBE Vector Shape - Group","hd":false},{"ty":"fl","c":{"a":0,"k":[0.851000019148,1,0.969000004787,1],"ix":4},"o":{"a":0,"k":100,"ix":5},"r":1,"bm":0,"nm":"Заливка 1","mn":"ADBE Vector Graphic - Fill","hd":false},{"ty":"tr","p":{"a":0,"k":[6.456,5.784],"ix":2},"a":{"a":0,"k":[0,0],"ix":1},"s":{"a":0,"k":[100,100],"ix":3},"r":{"a":0,"k":0,"ix":6},"o":{"a":0,"k":100,"ix":7},"sk":{"a":0,"k":0,"ix":4},"sa":{"a":0,"k":0,"ix":5},"nm":"Преобразовать"}],"nm":"Группа 1","np":2,"cix":2,"bm":0,"ix":1,"mn":"ADBE Vector Group","hd":false},{"ty":"gr","it":[{"ind":0,"ty":"sh","ix":1,"ks":{"a":0,"k":{"i":[[-4.895,-6.933],[2.226,-1.571],[4.894,6.932],[-2.225,1.572]],"o":[[4.895,6.933],[-2.225,1.571],[-4.894,-6.933],[2.225,-1.571]],"v":[[5.792,-3.669],[8.861,12.552],[0.23,-0.098],[-8.862,-12.552]],"c":true},"ix":2},"nm":"Контур 1","mn":"ADBE Vector Shape - Group","hd":false},{"ty":"fl","c":{"a":0,"k":[0.851000019148,1,0.969000004787,1],"ix":4},"o":{"a":0,"k":100,"ix":5},"r":1,"bm":0,"nm":"Заливка 1","mn":"ADBE Vector Graphic - Fill","hd":false},{"ty":"tr","p":{"a":0,"k":[25.026,26.761],"ix":2},"a":{"a":0,"k":[0,0],"ix":1},"s":{"a":0,"k":[100,100],"ix":3},"r":{"a":0,"k":0,"ix":6},"o":{"a":0,"k":100,"ix":7},"sk":{"a":0,"k":0,"ix":4},"sa":{"a":0,"k":0,"ix":5},"nm":"Преобразовать"}],"nm":"Группа 2","np":2,"cix":2,"bm":0,"ix":2,"mn":"ADBE Vector Group","hd":false}],"ip":0,"op":180,"st":0,"bm":0},{"ddd":0,"ind":7,"ty":4,"nm":"Кисть","parent":8,"sr":1,"ks":{"o":{"a":0,"k":100,"ix":11},"r":{"a":1,"k":[{"i":{"x":[0.833],"y":[0.833]},"o":{"x":[0.167],"y":[0.167]},"t":0,"s":[0]},{"i":{"x":[0.833],"y":[0.833]},"o":{"x":[0.167],"y":[0.167]},"t":84,"s":[23.686]},{"t":178,"s":[0]}],"ix":10},"p":{"a":0,"k":[7.686,5.765,0],"ix":2},"a":{"a":0,"k":[36.484,62.531,0],"ix":1},"s":{"a":0,"k":[102,102,100],"ix":6}},"ao":0,"shapes":[{"ty":"gr","it":[{"ind":0,"ty":"sh","ix":1,"ks":{"a":0,"k":{"i":[[0,0],[-4.178,0.809],[-0.449,3.684],[-6.957,1.184],[-5.032,12.148],[-3.869,-1.629],[-11.595,-1.456],[7.009,1.344],[-1.957,-9.294]],"o":[[-13.322,-9.046],[3.766,-0.729],[0.246,-2.019],[6.335,-1.078],[5.032,-12.149],[6.829,2.875],[14.295,1.796],[-7.512,-1.439],[0,0]],"v":[[-5.599,21.103],[-24.469,-12.593],[-7.711,7.445],[-7.891,-26.494],[3.836,4.794],[21.223,-19.467],[14.352,15.955],[20.35,23.836],[0.196,27.572]],"c":false},"ix":2},"nm":"Контур 1","mn":"ADBE Vector Shape - Group","hd":false},{"ty":"st","c":{"a":0,"k":[0.071000005685,0.149000010771,0.136999990426,1],"ix":3},"o":{"a":0,"k":100,"ix":4},"w":{"a":0,"k":3,"ix":5},"lc":2,"lj":1,"ml":10,"bm":0,"nm":"Обводка 1","mn":"ADBE Vector Graphic - Stroke","hd":false},{"ty":"tr","p":{"a":0,"k":[36.147,35.072],"ix":2},"a":{"a":0,"k":[0,0],"ix":1},"s":{"a":0,"k":[100,100],"ix":3},"r":{"a":0,"k":0,"ix":6},"o":{"a":0,"k":100,"ix":7},"sk":{"a":0,"k":0,"ix":4},"sa":{"a":0,"k":0,"ix":5},"nm":"Преобразовать"}],"nm":"Группа 1","np":2,"cix":2,"bm":0,"ix":1,"mn":"ADBE Vector Group","hd":false}],"ip":0,"op":180,"st":0,"bm":0},{"ddd":0,"ind":8,"ty":4,"nm":"Нить 2","parent":30,"sr":1,"ks":{"o":{"a":0,"k":100,"ix":11},"r":{"a":1,"k":[{"i":{"x":[0.58],"y":[1]},"o":{"x":[0.168],"y":[0]},"t":0,"s":[-0.832]},{"i":{"x":[0.833],"y":[1]},"o":{"x":[0.414],"y":[0]},"t":11,"s":[28.168]},{"i":{"x":[0.58],"y":[1]},"o":{"x":[0.168],"y":[0]},"t":22,"s":[-0.832]},{"i":{"x":[0.833],"y":[1]},"o":{"x":[0.414],"y":[0]},"t":33,"s":[28.168]},{"i":{"x":[0.58],"y":[1]},"o":{"x":[0.168],"y":[0]},"t":44,"s":[-0.832]},{"i":{"x":[0.833],"y":[1]},"o":{"x":[0.414],"y":[0]},"t":55,"s":[28.168]},{"i":{"x":[0.58],"y":[1]},"o":{"x":[0.168],"y":[0]},"t":66,"s":[-0.832]},{"i":{"x":[0.833],"y":[1]},"o":{"x":[0.414],"y":[0]},"t":77,"s":[28.168]},{"i":{"x":[0.58],"y":[1]},"o":{"x":[0.168],"y":[0]},"t":88,"s":[-0.832]},{"i":{"x":[0.833],"y":[1]},"o":{"x":[0.414],"y":[0]},"t":99,"s":[28.168]},{"i":{"x":[0.58],"y":[1]},"o":{"x":[0.168],"y":[0]},"t":110,"s":[-0.832]},{"i":{"x":[0.833],"y":[1]},"o":{"x":[0.414],"y":[0]},"t":122,"s":[28.168]},{"i":{"x":[0.58],"y":[1]},"o":{"x":[0.168],"y":[0]},"t":133,"s":[-0.832]},{"i":{"x":[0.833],"y":[1]},"o":{"x":[0.414],"y":[0]},"t":144,"s":[28.168]},{"i":{"x":[0.58],"y":[1]},"o":{"x":[0.168],"y":[0]},"t":155,"s":[-0.832]},{"i":{"x":[0.833],"y":[1]},"o":{"x":[0.414],"y":[0]},"t":168,"s":[28.168]},{"i":{"x":[0.58],"y":[1]},"o":{"x":[0.168],"y":[0]},"t":179,"s":[-0.832]},{"i":{"x":[0.58],"y":[1]},"o":{"x":[0.414],"y":[0]},"t":184,"s":[28.168]},{"i":{"x":[0.667],"y":[1]},"o":{"x":[0.414],"y":[0]},"t":192,"s":[28.168]},{"i":{"x":[0.833],"y":[1]},"o":{"x":[0.333],"y":[0]},"t":195,"s":[24.357]},{"i":{"x":[0.441],"y":[1.004]},"o":{"x":[0.168],"y":[0]},"t":203,"s":[-0.832]},{"i":{"x":[0.667],"y":[1]},"o":{"x":[0.167],"y":[0.002]},"t":208,"s":[20.969]},{"i":{"x":[0.667],"y":[1]},"o":{"x":[0.333],"y":[0]},"t":216,"s":[1.706]},{"i":{"x":[0.708],"y":[1.118]},"o":{"x":[0.333],"y":[0]},"t":235,"s":[24.709]},{"t":256,"s":[1.523]}],"ix":10},"p":{"a":1,"k":[{"i":{"x":0.833,"y":0.833},"o":{"x":0.167,"y":0.167},"t":0,"s":[92.615,261.24,0],"to":[0,0,0],"ti":[0,0,0]},{"t":179,"s":[92.615,261.24,0]}],"ix":2},"a":{"a":0,"k":[135.118,130.239,0],"ix":1},"s":{"a":0,"k":[100,100,100],"ix":6}},"ao":0,"shapes":[{"ty":"gr","it":[{"ind":0,"ty":"sh","ix":1,"ks":{"a":0,"k":{"i":[[0,0],[0,0]],"o":[[22.578,107.208],[0,0]],"v":[[-63.618,-60.739],[63.618,60.739]],"c":false},"ix":2},"nm":"Контур 1","mn":"ADBE Vector Shape - Group","hd":false},{"ty":"st","c":{"a":0,"k":[0.071000005685,0.149000010771,0.136999990426,1],"ix":3},"o":{"a":0,"k":100,"ix":4},"w":{"a":0,"k":3,"ix":5},"lc":2,"lj":1,"ml":10,"bm":0,"nm":"Обводка 1","mn":"ADBE Vector Graphic - Stroke","hd":false},{"ty":"tr","p":{"a":0,"k":[71.118,68.239],"ix":2},"a":{"a":0,"k":[0,0],"ix":1},"s":{"a":0,"k":[100,100],"ix":3},"r":{"a":0,"k":0,"ix":6},"o":{"a":0,"k":100,"ix":7},"sk":{"a":0,"k":0,"ix":4},"sa":{"a":0,"k":0,"ix":5},"nm":"Преобразовать"}],"nm":"Группа 1","np":2,"cix":2,"bm":0,"ix":1,"mn":"ADBE Vector Group","hd":false}],"ip":0,"op":180,"st":0,"bm":0},{"ddd":0,"ind":9,"ty":4,"nm":"Бровь","parent":3,"sr":1,"ks":{"o":{"a":0,"k":100,"ix":11},"r":{"a":0,"k":0,"ix":10},"p":{"a":0,"k":[284.615,177.092,0],"ix":2},"a":{"a":0,"k":[13.156,5.814,0],"ix":1},"s":{"a":0,"k":[130,130,100],"ix":6}},"ao":0,"shapes":[{"ty":"gr","it":[{"ind":0,"ty":"sh","ix":1,"ks":{"a":0,"k":{"i":[[-6.915,-1.202],[0.386,-2.22],[6.915,1.203],[-0.385,2.22]],"o":[[6.915,1.202],[-0.385,2.219],[-6.915,-1.201],[0.386,-2.219]],"v":[[1.25,-4.363],[12.521,3.346],[0.077,0.977],[-12.522,-1.007]],"c":true},"ix":2},"nm":"Контур 1","mn":"ADBE Vector Shape - Group","hd":false},{"ty":"fl","c":{"a":0,"k":[0.238999998803,0.522000002394,0.463000009574,1],"ix":4},"o":{"a":0,"k":100,"ix":5},"r":1,"bm":0,"nm":"Заливка 1","mn":"ADBE Vector Graphic - Fill","hd":false},{"ty":"tr","p":{"a":0,"k":[13.156,5.815],"ix":2},"a":{"a":0,"k":[0,0],"ix":1},"s":{"a":0,"k":[100,100],"ix":3},"r":{"a":0,"k":0,"ix":6},"o":{"a":0,"k":100,"ix":7},"sk":{"a":0,"k":0,"ix":4},"sa":{"a":0,"k":0,"ix":5},"nm":"Преобразовать"}],"nm":"Группа 1","np":2,"cix":2,"bm":0,"ix":1,"mn":"ADBE Vector Group","hd":false}],"ip":0,"op":180,"st":0,"bm":0},{"ddd":0,"ind":10,"ty":4,"nm":"Бровь","parent":3,"sr":1,"ks":{"o":{"a":0,"k":100,"ix":11},"r":{"a":0,"k":0,"ix":10},"p":{"a":0,"k":[196.123,177.099,0],"ix":2},"a":{"a":0,"k":[13.157,5.803,0],"ix":1},"s":{"a":0,"k":[130,130,100],"ix":6}},"ao":0,"shapes":[{"ty":"gr","it":[{"ind":0,"ty":"sh","ix":1,"ks":{"a":0,"k":{"i":[[-6.923,1.157],[-0.371,-2.223],[6.923,-1.156],[0.372,2.222]],"o":[[6.923,-1.157],[0.372,2.222],[-6.923,1.157],[-0.371,-2.222]],"v":[[-0.654,-4.397],[12.535,-0.858],[0.01,1.03],[-12.536,3.332]],"c":true},"ix":2},"nm":"Контур 1","mn":"ADBE Vector Shape - Group","hd":false},{"ty":"fl","c":{"a":0,"k":[0.238999998803,0.522000002394,0.463000009574,1],"ix":4},"o":{"a":0,"k":100,"ix":5},"r":1,"bm":0,"nm":"Заливка 1","mn":"ADBE Vector Graphic - Fill","hd":false},{"ty":"tr","p":{"a":0,"k":[13.157,5.804],"ix":2},"a":{"a":0,"k":[0,0],"ix":1},"s":{"a":0,"k":[100,100],"ix":3},"r":{"a":0,"k":0,"ix":6},"o":{"a":0,"k":100,"ix":7},"sk":{"a":0,"k":0,"ix":4},"sa":{"a":0,"k":0,"ix":5},"nm":"Преобразовать"}],"nm":"Группа 1","np":2,"cix":2,"bm":0,"ix":1,"mn":"ADBE Vector Group","hd":false}],"ip":0,"op":180,"st":0,"bm":0},{"ddd":0,"ind":11,"ty":4,"nm":"Ресница П","parent":4,"sr":1,"ks":{"o":{"a":0,"k":100,"ix":11},"r":{"a":0,"k":-11,"ix":10},"p":{"a":0,"k":[-97.155,89.744,0],"ix":2},"a":{"a":0,"k":[17.749,10.694,0],"ix":1},"s":{"a":0,"k":[142.857,158.537,100],"ix":6}},"ao":0,"shapes":[{"ty":"gr","it":[{"ind":0,"ty":"sh","ix":1,"ks":{"a":0,"k":{"i":[[0.408,-4.055],[2.33,3.139],[3.675,1.172],[3.754,-1.088],[2.651,-3.114],[-3.984,1.459],[-4.076,-1.283],[-1.717,-1.273],[-1.127,-1.805]],"o":[[-0.458,-4.059],[-2.303,-3.137],[-3.672,-1.19],[-3.763,1.084],[1.986,-3.579],[3.973,-1.501],[2.042,0.637],[1.697,1.303],[2.301,3.602]],"v":[[17.091,10.444],[13.071,-0.652],[3.793,-7.27],[-7.674,-7.445],[-17.499,-0.952],[-8.153,-8.889],[4.396,-9.161],[10.079,-6.241],[14.392,-1.551]],"c":true},"ix":2},"nm":"Контур 1","mn":"ADBE Vector Shape - Group","hd":false},{"ty":"fl","c":{"a":0,"k":[0.149000010771,0.310000011968,0.282000014361,1],"ix":4},"o":{"a":0,"k":100,"ix":5},"r":1,"bm":0,"nm":"Заливка 1","mn":"ADBE Vector Graphic - Fill","hd":false},{"ty":"tr","p":{"a":0,"k":[17.749,10.695],"ix":2},"a":{"a":0,"k":[0,0],"ix":1},"s":{"a":0,"k":[100,100],"ix":3},"r":{"a":0,"k":0,"ix":6},"o":{"a":0,"k":100,"ix":7},"sk":{"a":0,"k":0,"ix":4},"sa":{"a":0,"k":0,"ix":5},"nm":"Преобразовать"}],"nm":"Группа 1","np":2,"cix":2,"bm":0,"ix":1,"mn":"ADBE Vector Group","hd":false}],"ip":0,"op":180,"st":0,"bm":0},{"ddd":0,"ind":12,"ty":4,"nm":"Ресница Л","parent":4,"sr":1,"ks":{"o":{"a":0,"k":100,"ix":11},"r":{"a":0,"k":17,"ix":10},"p":{"a":0,"k":[-181.98,90.135,0],"ix":2},"a":{"a":0,"k":[17.529,10.712,0],"ix":1},"s":{"a":0,"k":[142.857,158.537,100],"ix":6}},"ao":0,"shapes":[{"ty":"gr","it":[{"ind":0,"ty":"sh","ix":1,"ks":{"a":0,"k":{"i":[[0.46,-4.029],[-2.237,3.606],[-1.669,1.316],[-2.026,0.65],[-3.94,-1.511],[-1.968,-3.553],[3.732,1.088],[3.63,-1.21],[2.249,-3.143]],"o":[[-0.405,-4.026],[1.095,-1.806],[1.691,-1.288],[4.041,-1.309],[3.954,1.467],[-2.633,-3.089],[-3.72,-1.097],[-3.635,1.192],[-2.273,3.146]],"v":[[-16.873,10.461],[-14.277,-1.474],[-10.057,-6.189],[-4.438,-9.152],[8.027,-8.905],[17.279,-0.984],[7.543,-7.462],[-3.82,-7.266],[-12.947,-0.591]],"c":true},"ix":2},"nm":"Контур 1","mn":"ADBE Vector Shape - Group","hd":false},{"ty":"fl","c":{"a":0,"k":[0.149000010771,0.310000011968,0.282000014361,1],"ix":4},"o":{"a":0,"k":100,"ix":5},"r":1,"bm":0,"nm":"Заливка 1","mn":"ADBE Vector Graphic - Fill","hd":false},{"ty":"tr","p":{"a":0,"k":[17.528,10.712],"ix":2},"a":{"a":0,"k":[0,0],"ix":1},"s":{"a":0,"k":[100,100],"ix":3},"r":{"a":0,"k":0,"ix":6},"o":{"a":0,"k":100,"ix":7},"sk":{"a":0,"k":0,"ix":4},"sa":{"a":0,"k":0,"ix":5},"nm":"Преобразовать"}],"nm":"Группа 1","np":2,"cix":2,"bm":0,"ix":1,"mn":"ADBE Vector Group","hd":false}],"ip":0,"op":180,"st":0,"bm":0},{"ddd":0,"ind":13,"ty":4,"nm":"Слой-фигура 3","parent":11,"sr":1,"ks":{"o":{"a":0,"k":100,"ix":11},"r":{"a":0,"k":9.935,"ix":10},"p":{"a":0,"k":[-17.069,1.04,0],"ix":2},"a":{"a":0,"k":[0,0,0],"ix":1},"s":{"a":0,"k":[76.659,222.084,100],"ix":6}},"ao":0,"shapes":[{"ty":"gr","it":[{"ind":0,"ty":"sh","ix":1,"ks":{"a":0,"k":{"i":[[19,-3],[-5.5,-20.25],[-11.5,-1],[-7.335,-10.269],[4.75,10.75]],"o":[[-19,3],[9,-4],[11.5,1],[2.25,-16.75],[-4.75,-10.75]],"v":[[41,-47.25],[22,3.5],[48.5,-2.25],[76.75,9.25],[75.25,-34]],"c":true},"ix":2},"nm":"Контур 1","mn":"ADBE Vector Shape - Group","hd":false},{"ty":"fl","c":{"a":0,"k":[0.384313755409,0.831372608858,0.741176470588,1],"ix":4},"o":{"a":0,"k":100,"ix":5},"r":1,"bm":0,"nm":"Заливка 1","mn":"ADBE Vector Graphic - Fill","hd":false},{"ty":"tr","p":{"a":0,"k":[0,0],"ix":2},"a":{"a":0,"k":[0,0],"ix":1},"s":{"a":0,"k":[100,100],"ix":3},"r":{"a":0,"k":0,"ix":6},"o":{"a":0,"k":100,"ix":7},"sk":{"a":0,"k":0,"ix":4},"sa":{"a":0,"k":0,"ix":5},"nm":"Преобразовать"}],"nm":"Фигура 1","np":3,"cix":2,"bm":0,"ix":1,"mn":"ADBE Vector Group","hd":false}],"ip":0,"op":180,"st":0,"bm":0},{"ddd":0,"ind":14,"ty":4,"nm":"Слой-фигура 2","parent":12,"sr":1,"ks":{"o":{"a":0,"k":100,"ix":11},"r":{"a":0,"k":-15.403,"ix":10},"p":{"a":0,"k":[38.459,1.037,0],"ix":2},"a":{"a":0,"k":[0,0,0],"ix":1},"s":{"a":0,"k":[76.302,244.724,100],"ix":6}},"ao":0,"shapes":[{"ty":"gr","it":[{"ind":0,"ty":"sh","ix":1,"ks":{"a":0,"k":{"i":[[8,-1.25],[-3.25,-44],[-12.75,0.125],[-2.75,-3.25],[8,10.5]],"o":[[-8,1.25],[7.75,-5],[14.625,-0.143],[0.75,-12.5],[-8,-10.5]],"v":[[-38.234,-31.976],[-56.25,4.5],[-31,-2.625],[-4.5,5.25],[-10,-31.5]],"c":true},"ix":2},"nm":"Контур 1","mn":"ADBE Vector Shape - Group","hd":false},{"ty":"fl","c":{"a":0,"k":[0.384313755409,0.831372608858,0.741176470588,1],"ix":4},"o":{"a":0,"k":100,"ix":5},"r":1,"bm":0,"nm":"Заливка 1","mn":"ADBE Vector Graphic - Fill","hd":false},{"ty":"tr","p":{"a":0,"k":[0,0],"ix":2},"a":{"a":0,"k":[0,0],"ix":1},"s":{"a":0,"k":[100,100],"ix":3},"r":{"a":0,"k":0,"ix":6},"o":{"a":0,"k":100,"ix":7},"sk":{"a":0,"k":0,"ix":4},"sa":{"a":0,"k":0,"ix":5},"nm":"Преобразовать"}],"nm":"Фигура 1","np":3,"cix":2,"bm":0,"ix":1,"mn":"ADBE Vector Group","hd":false}],"ip":0,"op":180,"st":0,"bm":0},{"ddd":0,"ind":15,"ty":4,"nm":"Рот","parent":2,"sr":1,"ks":{"o":{"a":0,"k":100,"ix":11},"r":{"a":0,"k":0,"ix":10},"p":{"a":0,"k":[237.377,-11.197,0],"ix":2},"a":{"a":0,"k":[20.033,23.513,0],"ix":1},"s":{"a":0,"k":[130,130,100],"ix":6}},"ao":0,"shapes":[{"ty":"gr","it":[{"ind":0,"ty":"sh","ix":1,"ks":{"a":0,"k":{"i":[[0,0],[-4.114,-2.156],[0.436,-3.119],[4.266,-5.662],[3.532,-1.58]],"o":[[0,0],[0,0],[-0.859,-1.636],[-1.328,-3.707],[-0.749,-2.236]],"v":[[-14.421,-1.468],[14.408,-1.024],[14.014,2.659],[-0.007,3.18],[-13.702,1.178]],"c":true},"ix":2},"nm":"Контур 1","mn":"ADBE Vector Shape - Group","hd":false},{"ty":"fl","c":{"a":0,"k":[0.654999976065,0.838999968884,0.8,1],"ix":4},"o":{"a":0,"k":100,"ix":5},"r":1,"bm":0,"nm":"Заливка 1","mn":"ADBE Vector Graphic - Fill","hd":false},{"ty":"tr","p":{"a":0,"k":[20.363,3.43],"ix":2},"a":{"a":0,"k":[0,0],"ix":1},"s":{"a":0,"k":[100,100],"ix":3},"r":{"a":0,"k":0,"ix":6},"o":{"a":0,"k":100,"ix":7},"sk":{"a":0,"k":0,"ix":4},"sa":{"a":0,"k":0,"ix":5},"nm":"Преобразовать"}],"nm":"Группа 1","np":2,"cix":2,"bm":0,"ix":1,"mn":"ADBE Vector Group","hd":false},{"ty":"gr","it":[{"ind":0,"ty":"sh","ix":1,"ks":{"a":0,"k":{"i":[[0,3.119],[5.754,0],[0,-3.119],[-5.754,0]],"o":[[0,-3.119],[-5.754,0],[0,3.119],[5.754,0]],"v":[[10.418,0],[0,-5.647],[-10.418,0],[0,5.647]],"c":true},"ix":2},"nm":"Контур 1","mn":"ADBE Vector Shape - Group","hd":false},{"ty":"fl","c":{"a":0,"k":[0.368999974868,0.258999992819,0.258999992819,1],"ix":4},"o":{"a":0,"k":100,"ix":5},"r":1,"bm":0,"nm":"Заливка 1","mn":"ADBE Vector Graphic - Fill","hd":false},{"ty":"tr","p":{"a":0,"k":[20.033,21.968],"ix":2},"a":{"a":0,"k":[0,0],"ix":1},"s":{"a":1,"k":[{"i":{"x":[0.833,0.833],"y":[0.833,0.833]},"o":{"x":[0.167,0.167],"y":[0.167,0.167]},"t":0,"s":[100,100]},{"i":{"x":[0.833,0.833],"y":[0.833,0.833]},"o":{"x":[0.167,0.167],"y":[0.167,0.167]},"t":21,"s":[107,50]},{"t":48,"s":[100,100]}],"ix":3},"r":{"a":0,"k":0,"ix":6},"o":{"a":0,"k":100,"ix":7},"sk":{"a":0,"k":0,"ix":4},"sa":{"a":0,"k":0,"ix":5},"nm":"Преобразовать"}],"nm":"Группа 2","np":2,"cix":2,"bm":0,"ix":2,"mn":"ADBE Vector Group","hd":false},{"ty":"gr","it":[{"ind":0,"ty":"sh","ix":1,"ks":{"a":0,"k":{"i":[[6.919,0.831],[0.101,3.291],[-4.69,-0.442]],"o":[[-6.183,-0.742],[4.352,0.018],[-0.065,5.407]],"v":[[-1.409,5.178],[-7.214,-6.01],[7.592,-5.225]],"c":true},"ix":2},"nm":"Контур 1","mn":"ADBE Vector Shape - Group","hd":false},{"ty":"fl","c":{"a":0,"k":[0.851000019148,1,0.969000004787,1],"ix":4},"o":{"a":0,"k":100,"ix":5},"r":1,"bm":0,"nm":"Заливка 1","mn":"ADBE Vector Graphic - Fill","hd":false},{"ty":"tr","p":{"a":0,"k":[27.178,7.631],"ix":2},"a":{"a":0,"k":[0,0],"ix":1},"s":{"a":0,"k":[100,100],"ix":3},"r":{"a":0,"k":0,"ix":6},"o":{"a":0,"k":100,"ix":7},"sk":{"a":0,"k":0,"ix":4},"sa":{"a":0,"k":0,"ix":5},"nm":"Преобразовать"}],"nm":"Группа 3","np":2,"cix":2,"bm":0,"ix":3,"mn":"ADBE Vector Group","hd":false},{"ty":"gr","it":[{"ind":0,"ty":"sh","ix":1,"ks":{"a":0,"k":{"i":[[5.526,-0.045],[0.383,2.518],[-4.766,-0.032]],"o":[[-4.987,0.04],[4.389,-0.269],[-0.629,5.49]],"v":[[-0.292,4.48],[-7.839,-4.066],[7.839,-4.488]],"c":true},"ix":2},"nm":"Контур 1","mn":"ADBE Vector Shape - Group","hd":false},{"ty":"fl","c":{"a":0,"k":[0.851000019148,1,0.969000004787,1],"ix":4},"o":{"a":0,"k":100,"ix":5},"r":1,"bm":0,"nm":"Заливка 1","mn":"ADBE Vector Graphic - Fill","hd":false},{"ty":"tr","p":{"a":0,"k":[13.795,6.094],"ix":2},"a":{"a":0,"k":[0,0],"ix":1},"s":{"a":0,"k":[100,100],"ix":3},"r":{"a":0,"k":0,"ix":6},"o":{"a":0,"k":100,"ix":7},"sk":{"a":0,"k":0,"ix":4},"sa":{"a":0,"k":0,"ix":5},"nm":"Преобразовать"}],"nm":"Группа 4","np":2,"cix":2,"bm":0,"ix":4,"mn":"ADBE Vector Group","hd":false},{"ty":"gr","it":[{"ind":0,"ty":"sh","ix":1,"ks":{"a":0,"k":{"i":[[-0.637,-0.075],[2.753,38.81],[-1.305,0.076],[-4.767,-0.032],[-0.129,-0.011],[-5.628,-0.603]],"o":[[-5.544,40.157],[1.24,-0.108],[4.388,-0.269],[0.128,-0.011],[6.286,0.033],[0.658,0.076]],"v":[[19.14,-19.475],[-19.14,-20.014],[-15.322,-20.284],[-1.423,-20.651],[-1.036,-20.651],[17.199,-19.702]],"c":true},"ix":2},"nm":"Контур 1","mn":"ADBE Vector Shape - Group","hd":false},{"ty":"fl","c":{"a":0,"k":[0.071000005685,0.149000010771,0.136999990426,1],"ix":4},"o":{"a":0,"k":100,"ix":5},"r":1,"bm":0,"nm":"Заливка 1","mn":"ADBE Vector Graphic - Fill","hd":false},{"ty":"tr","p":{"a":0,"k":[20.001,22.318],"ix":2},"a":{"a":0,"k":[0,0],"ix":1},"s":{"a":1,"k":[{"i":{"x":[0.833,0.833],"y":[0.833,0.833]},"o":{"x":[0.167,0.167],"y":[0.167,0.167]},"t":0,"s":[100,100]},{"i":{"x":[0.833,0.833],"y":[0.833,0.833]},"o":{"x":[0.167,0.167],"y":[0.167,0.167]},"t":16,"s":[98,100]},{"t":28,"s":[100,100]}],"ix":3},"r":{"a":0,"k":0,"ix":6},"o":{"a":0,"k":100,"ix":7},"sk":{"a":0,"k":0,"ix":4},"sa":{"a":0,"k":0,"ix":5},"nm":"Преобразовать"}],"nm":"Группа 5","np":2,"cix":2,"bm":0,"ix":5,"mn":"ADBE Vector Group","hd":false},{"ty":"gr","it":[{"ind":0,"ty":"sh","ix":1,"ks":{"a":0,"k":{"i":[[-0.67,-0.08],[2.246,42.25],[-1.374,0.08],[-5.017,-0.034],[-0.135,-0.012],[-5.926,-0.643]],"o":[[-5.046,43.834],[1.306,-0.115],[4.621,-0.287],[0.136,-0.012],[6.62,0.034],[0.692,0.08]],"v":[[19.783,-21.293],[-19.783,-21.866],[-16.192,-22.116],[-1.559,-22.507],[-1.151,-22.507],[18.047,-21.497]],"c":true},"ix":2},"nm":"Контур 1","mn":"ADBE Vector Shape - Group","hd":false},{"ty":"fl","c":{"a":0,"k":[0.505999995213,0.987999949736,0.917999985639,1],"ix":4},"o":{"a":0,"k":100,"ix":5},"r":1,"bm":0,"nm":"Заливка 1","mn":"ADBE Vector Graphic - Fill","hd":false},{"ty":"tr","p":{"a":0,"k":[20.033,24.235],"ix":2},"a":{"a":0,"k":[0,0],"ix":1},"s":{"a":0,"k":[100,100],"ix":3},"r":{"a":0,"k":0,"ix":6},"o":{"a":0,"k":100,"ix":7},"sk":{"a":0,"k":0,"ix":4},"sa":{"a":0,"k":0,"ix":5},"nm":"Преобразовать"}],"nm":"Группа 6","np":2,"cix":2,"bm":0,"ix":6,"mn":"ADBE Vector Group","hd":false}],"ip":0,"op":180,"st":0,"bm":0},{"ddd":0,"ind":16,"ty":4,"nm":"Румяна","parent":2,"sr":1,"ks":{"o":{"a":0,"k":100,"ix":11},"r":{"a":0,"k":0,"ix":10},"p":{"a":1,"k":[{"i":{"x":0.667,"y":1},"o":{"x":0.333,"y":0},"t":0,"s":[187.961,-33.849,0],"to":[0,-1.5,0],"ti":[0,0,0]},{"i":{"x":0.667,"y":1},"o":{"x":0.333,"y":0},"t":10,"s":[187.961,-42.849,0],"to":[0,0,0],"ti":[0,-1.5,0]},{"t":20,"s":[187.961,-33.849,0]}],"ix":2},"a":{"a":0,"k":[10.481,10.481,0],"ix":1},"s":{"a":1,"k":[{"i":{"x":[0.667,0.667,0.667],"y":[1,1,1]},"o":{"x":[0.333,0.333,0.333],"y":[0,0,0]},"t":0,"s":[130,130,100]},{"i":{"x":[0.667,0.667,0.667],"y":[1,1,1]},"o":{"x":[0.333,0.333,0.333],"y":[0,0,0]},"t":10,"s":[130,80,100]},{"t":20,"s":[130,130,100]}],"ix":6}},"ao":0,"shapes":[{"ty":"gr","it":[{"ind":0,"ty":"sh","ix":1,"ks":{"a":0,"k":{"i":[[0,5.65],[5.65,0],[0,-5.651],[-5.651,0]],"o":[[0,-5.651],[-5.651,0],[0,5.65],[5.65,0]],"v":[[10.232,0],[0.001,-10.231],[-10.232,0],[0.001,10.231]],"c":true},"ix":2},"nm":"Контур 1","mn":"ADBE Vector Shape - Group","hd":false},{"ty":"fl","c":{"a":0,"k":[0.677999997606,0.603999956916,0.603999956916,1],"ix":4},"o":{"a":0,"k":100,"ix":5},"r":1,"bm":0,"nm":"Заливка 1","mn":"ADBE Vector Graphic - Fill","hd":false},{"ty":"tr","p":{"a":0,"k":[10.481,10.482],"ix":2},"a":{"a":0,"k":[0,0],"ix":1},"s":{"a":0,"k":[100,100],"ix":3},"r":{"a":0,"k":0,"ix":6},"o":{"a":0,"k":100,"ix":7},"sk":{"a":0,"k":0,"ix":4},"sa":{"a":0,"k":0,"ix":5},"nm":"Преобразовать"}],"nm":"Группа 1","np":2,"cix":2,"bm":0,"ix":1,"mn":"ADBE Vector Group","hd":false}],"ip":0,"op":180,"st":0,"bm":0},{"ddd":0,"ind":17,"ty":4,"nm":"Румяна","parent":2,"sr":1,"ks":{"o":{"a":0,"k":100,"ix":11},"r":{"a":0,"k":0,"ix":10},"p":{"a":1,"k":[{"i":{"x":0.667,"y":1},"o":{"x":0.333,"y":0},"t":0,"s":[284.284,-31.39,0],"to":[0,-1.5,0],"ti":[0,0,0]},{"i":{"x":0.667,"y":1},"o":{"x":0.333,"y":0},"t":10,"s":[284.284,-40.39,0],"to":[0,0,0],"ti":[0,-1.5,0]},{"t":20,"s":[284.284,-31.39,0]}],"ix":2},"a":{"a":0,"k":[10.481,10.481,0],"ix":1},"s":{"a":1,"k":[{"i":{"x":[0.667,0.667,0.667],"y":[1,1,1]},"o":{"x":[0.333,0.333,0.333],"y":[0,0,0]},"t":0,"s":[130,130,100]},{"i":{"x":[0.667,0.667,0.667],"y":[1,1,1]},"o":{"x":[0.333,0.333,0.333],"y":[0,0,0]},"t":10,"s":[130,80,100]},{"t":20,"s":[130,130,100]}],"ix":6}},"ao":0,"shapes":[{"ty":"gr","it":[{"ind":0,"ty":"sh","ix":1,"ks":{"a":0,"k":{"i":[[0,5.651],[5.651,0],[0,-5.65],[-5.651,0]],"o":[[0,-5.65],[-5.651,0],[0,5.651],[5.651,0]],"v":[[10.232,0],[0,-10.231],[-10.232,0],[0,10.231]],"c":true},"ix":2},"nm":"Контур 1","mn":"ADBE Vector Shape - Group","hd":false},{"ty":"fl","c":{"a":0,"k":[0.677999997606,0.603999956916,0.603999956916,1],"ix":4},"o":{"a":0,"k":100,"ix":5},"r":1,"bm":0,"nm":"Заливка 1","mn":"ADBE Vector Graphic - Fill","hd":false},{"ty":"tr","p":{"a":0,"k":[10.482,10.481],"ix":2},"a":{"a":0,"k":[0,0],"ix":1},"s":{"a":0,"k":[100,100],"ix":3},"r":{"a":0,"k":0,"ix":6},"o":{"a":0,"k":100,"ix":7},"sk":{"a":0,"k":0,"ix":4},"sa":{"a":0,"k":0,"ix":5},"nm":"Преобразовать"}],"nm":"Группа 1","np":2,"cix":2,"bm":0,"ix":1,"mn":"ADBE Vector Group","hd":false}],"ip":0,"op":180,"st":0,"bm":0},{"ddd":0,"ind":18,"ty":4,"nm":"Слой-фигураНИЗ ВЕКО","parent":30,"sr":1,"ks":{"o":{"a":0,"k":100,"ix":11},"r":{"a":0,"k":0,"ix":10},"p":{"a":1,"k":[{"i":{"x":0.667,"y":1},"o":{"x":0.333,"y":0},"t":0,"s":[97.2,174.096,0],"to":[0,-2.821,0],"ti":[0,0,0]},{"i":{"x":0.667,"y":1},"o":{"x":0.333,"y":0},"t":10,"s":[97.2,157.173,0],"to":[0,0,0],"ti":[0,-2.821,0]},{"t":20,"s":[97.2,174.096,0]}],"ix":2},"a":{"a":0,"k":[0,0,0],"ix":1},"s":{"a":0,"k":[76.923,76.923,100],"ix":6}},"ao":0,"shapes":[{"ty":"gr","it":[{"ind":0,"ty":"sh","ix":1,"ks":{"a":0,"k":{"i":[[13.25,0.75],[6.75,-3.5],[-14.25,-0.25],[-2,6]],"o":[[-13.25,-0.75],[-6.75,3.5],[14.25,0.25],[-3.75,-6.75]],"v":[[47,-2],[22.75,3.75],[50.25,21.25],[72.75,6]],"c":true},"ix":2},"nm":"Контур 1","mn":"ADBE Vector Shape - Group","hd":false},{"ty":"fl","c":{"a":0,"k":[0.384313755409,0.831372608858,0.741176470588,1],"ix":4},"o":{"a":0,"k":100,"ix":5},"r":1,"bm":0,"nm":"Заливка 1","mn":"ADBE Vector Graphic - Fill","hd":false},{"ty":"tr","p":{"a":0,"k":[0,0],"ix":2},"a":{"a":0,"k":[0,0],"ix":1},"s":{"a":0,"k":[100,100],"ix":3},"r":{"a":0,"k":0,"ix":6},"o":{"a":0,"k":100,"ix":7},"sk":{"a":0,"k":0,"ix":4},"sa":{"a":0,"k":0,"ix":5},"nm":"Преобразовать"}],"nm":"Фигура 2","np":3,"cix":2,"bm":0,"ix":1,"mn":"ADBE Vector Group","hd":false},{"ty":"gr","it":[{"ind":0,"ty":"sh","ix":1,"ks":{"a":0,"k":{"i":[[15.5,1.5],[6.5,-4],[-18.25,-0.75],[0,5.75]],"o":[[-15.5,-1.5],[-8.25,4.5],[18.25,0.75],[-3.25,-3.5]],"v":[[-30.25,-1.75],[-56.5,5.5],[-29.5,21.75],[-5,5]],"c":true},"ix":2},"nm":"Контур 1","mn":"ADBE Vector Shape - Group","hd":false},{"ty":"fl","c":{"a":0,"k":[0.384313755409,0.831372608858,0.741176470588,1],"ix":4},"o":{"a":0,"k":100,"ix":5},"r":1,"bm":0,"nm":"Заливка 1","mn":"ADBE Vector Graphic - Fill","hd":false},{"ty":"tr","p":{"a":0,"k":[0,0],"ix":2},"a":{"a":0,"k":[0,0],"ix":1},"s":{"a":0,"k":[100,100],"ix":3},"r":{"a":0,"k":0,"ix":6},"o":{"a":0,"k":100,"ix":7},"sk":{"a":0,"k":0,"ix":4},"sa":{"a":0,"k":0,"ix":5},"nm":"Преобразовать"}],"nm":"Фигура 1","np":3,"cix":2,"bm":0,"ix":2,"mn":"ADBE Vector Group","hd":false}],"ip":0,"op":180,"st":0,"bm":0},{"ddd":0,"ind":19,"ty":4,"nm":"Блеск в глазах","parent":30,"sr":1,"ks":{"o":{"a":0,"k":100,"ix":11},"r":{"a":0,"k":0,"ix":10},"p":{"a":0,"k":[133.335,151.589,0],"ix":2},"a":{"a":0,"k":[5.326,5.276,0],"ix":1},"s":{"a":0,"k":[100,100,100],"ix":6}},"ao":0,"shapes":[{"ty":"gr","it":[{"ind":0,"ty":"sh","ix":1,"ks":{"a":0,"k":{"i":[[1.315,1.629],[-1.082,-1.213]],"o":[[-0.987,-1.222],[0.966,1.084]],"v":[[-1.225,0.865],[1.247,-1.281]],"c":true},"ix":2},"nm":"Контур 1","mn":"ADBE Vector Shape - Group","hd":false},{"ty":"fl","c":{"a":0,"k":[0.607999973671,0.74900004069,0.722000002394,1],"ix":4},"o":{"a":0,"k":100,"ix":5},"r":1,"bm":0,"nm":"Заливка 1","mn":"ADBE Vector Graphic - Fill","hd":false},{"ty":"tr","p":{"a":0,"k":[2.462,7.807],"ix":2},"a":{"a":0,"k":[0,0],"ix":1},"s":{"a":0,"k":[100,100],"ix":3},"r":{"a":0,"k":0,"ix":6},"o":{"a":0,"k":100,"ix":7},"sk":{"a":0,"k":0,"ix":4},"sa":{"a":0,"k":0,"ix":5},"nm":"Преобразовать"}],"nm":"Группа 1","np":2,"cix":2,"bm":0,"ix":1,"mn":"ADBE Vector Group","hd":false},{"ty":"gr","it":[{"ind":0,"ty":"sh","ix":1,"ks":{"a":0,"k":{"i":[[0.821,-3.151],[-0.518,2.474]],"o":[[-0.616,2.365],[0.463,-2.209]],"v":[[2.334,0.475],[-2.636,-0.632]],"c":true},"ix":2},"nm":"Контур 1","mn":"ADBE Vector Shape - Group","hd":false},{"ty":"fl","c":{"a":0,"k":[0.607999973671,0.74900004069,0.722000002394,1],"ix":4},"o":{"a":0,"k":100,"ix":5},"r":1,"bm":0,"nm":"Заливка 1","mn":"ADBE Vector Graphic - Fill","hd":false},{"ty":"tr","p":{"a":0,"k":[7.247,3.091],"ix":2},"a":{"a":0,"k":[0,0],"ix":1},"s":{"a":0,"k":[100,100],"ix":3},"r":{"a":0,"k":0,"ix":6},"o":{"a":0,"k":100,"ix":7},"sk":{"a":0,"k":0,"ix":4},"sa":{"a":0,"k":0,"ix":5},"nm":"Преобразовать"}],"nm":"Группа 2","np":2,"cix":2,"bm":0,"ix":2,"mn":"ADBE Vector Group","hd":false}],"ip":0,"op":180,"st":0,"bm":0},{"ddd":0,"ind":20,"ty":4,"nm":"Блеск в лазах","parent":30,"sr":1,"ks":{"o":{"a":0,"k":100,"ix":11},"r":{"a":0,"k":0,"ix":10},"p":{"a":0,"k":[74.767,151.138,0],"ix":2},"a":{"a":0,"k":[6.202,5.216,0],"ix":1},"s":{"a":0,"k":[100,100,100],"ix":6}},"ao":0,"shapes":[{"ty":"gr","it":[{"ind":0,"ty":"sh","ix":1,"ks":{"a":0,"k":{"i":[[1.316,1.629],[-1.082,-1.214]],"o":[[-0.987,-1.223],[0.966,1.084]],"v":[[-1.225,0.866],[1.247,-1.281]],"c":true},"ix":2},"nm":"Контур 1","mn":"ADBE Vector Shape - Group","hd":false},{"ty":"fl","c":{"a":0,"k":[0.607999973671,0.74900004069,0.722000002394,1],"ix":4},"o":{"a":0,"k":100,"ix":5},"r":1,"bm":0,"nm":"Заливка 1","mn":"ADBE Vector Graphic - Fill","hd":false},{"ty":"tr","p":{"a":0,"k":[2.462,7.687],"ix":2},"a":{"a":0,"k":[0,0],"ix":1},"s":{"a":0,"k":[100,100],"ix":3},"r":{"a":0,"k":0,"ix":6},"o":{"a":0,"k":100,"ix":7},"sk":{"a":0,"k":0,"ix":4},"sa":{"a":0,"k":0,"ix":5},"nm":"Преобразовать"}],"nm":"Группа 1","np":2,"cix":2,"bm":0,"ix":1,"mn":"ADBE Vector Group","hd":false},{"ty":"gr","it":[{"ind":0,"ty":"sh","ix":1,"ks":{"a":0,"k":{"i":[[0.821,-3.151],[-0.518,2.474]],"o":[[-0.616,2.365],[0.463,-2.209]],"v":[[2.334,0.475],[-2.637,-0.632]],"c":true},"ix":2},"nm":"Контур 1","mn":"ADBE Vector Shape - Group","hd":false},{"ty":"fl","c":{"a":0,"k":[0.607999973671,0.74900004069,0.722000002394,1],"ix":4},"o":{"a":0,"k":100,"ix":5},"r":1,"bm":0,"nm":"Заливка 1","mn":"ADBE Vector Graphic - Fill","hd":false},{"ty":"tr","p":{"a":0,"k":[8.999,3.091],"ix":2},"a":{"a":0,"k":[0,0],"ix":1},"s":{"a":0,"k":[100,100],"ix":3},"r":{"a":0,"k":0,"ix":6},"o":{"a":0,"k":100,"ix":7},"sk":{"a":0,"k":0,"ix":4},"sa":{"a":0,"k":0,"ix":5},"nm":"Преобразовать"}],"nm":"Группа 2","np":2,"cix":2,"bm":0,"ix":2,"mn":"ADBE Vector Group","hd":false}],"ip":0,"op":180,"st":0,"bm":0},{"ddd":0,"ind":21,"ty":4,"nm":"Нижний блеск в глазах","parent":30,"sr":1,"ks":{"o":{"a":0,"k":100,"ix":11},"r":{"a":0,"k":0,"ix":10},"p":{"a":0,"k":[135.001,160.313,0],"ix":2},"a":{"a":0,"k":[7.18,2.96,0],"ix":1},"s":{"a":0,"k":[100,100,100],"ix":6}},"ao":0,"shapes":[{"ty":"gr","it":[{"ind":0,"ty":"sh","ix":1,"ks":{"a":0,"k":{"i":[[1.753,-2.768],[2.319,0],[-0.314,1.501],[-3.247,0.202]],"o":[[-0.689,1.09],[-4.146,-0.001],[0.2,-0.956],[4.777,-0.297]],"v":[[5.177,0.058],[-0.511,2.71],[-6.616,-0.553],[-0.425,-0.284]],"c":true},"ix":2},"nm":"Контур 1","mn":"ADBE Vector Shape - Group","hd":false},{"ty":"fl","c":{"a":0,"k":[0.231000010173,0.501999978458,0.442999985639,1],"ix":4},"o":{"a":0,"k":100,"ix":5},"r":1,"bm":0,"nm":"Заливка 1","mn":"ADBE Vector Graphic - Fill","hd":false},{"ty":"tr","p":{"a":0,"k":[7.18,2.96],"ix":2},"a":{"a":0,"k":[0,0],"ix":1},"s":{"a":0,"k":[100,100],"ix":3},"r":{"a":0,"k":0,"ix":6},"o":{"a":0,"k":100,"ix":7},"sk":{"a":0,"k":0,"ix":4},"sa":{"a":0,"k":0,"ix":5},"nm":"Преобразовать"}],"nm":"Группа 1","np":2,"cix":2,"bm":0,"ix":1,"mn":"ADBE Vector Group","hd":false}],"ip":0,"op":180,"st":0,"bm":0},{"ddd":0,"ind":22,"ty":4,"nm":"Нижний блеск в глазах","parent":30,"sr":1,"ks":{"o":{"a":0,"k":100,"ix":11},"r":{"a":0,"k":0,"ix":10},"p":{"a":0,"k":[76.288,160.235,0],"ix":2},"a":{"a":0,"k":[7.223,3.863,0],"ix":1},"s":{"a":0,"k":[100,100,100],"ix":6}},"ao":0,"shapes":[{"ty":"gr","it":[{"ind":0,"ty":"sh","ix":1,"ks":{"a":0,"k":{"i":[[1.826,-3.272],[2.905,-0.391],[-0.315,1.501],[-2.965,0.496]],"o":[[-0.865,1.55],[-3.841,0.517],[0.2,-0.956],[4.72,-0.789]],"v":[[5.147,-0.341],[-0.806,3.096],[-6.658,-0.79],[-0.482,-0.038]],"c":true},"ix":2},"nm":"Контур 1","mn":"ADBE Vector Shape - Group","hd":false},{"ty":"fl","c":{"a":0,"k":[0.231000010173,0.501999978458,0.442999985639,1],"ix":4},"o":{"a":0,"k":100,"ix":5},"r":1,"bm":0,"nm":"Заливка 1","mn":"ADBE Vector Graphic - Fill","hd":false},{"ty":"tr","p":{"a":0,"k":[7.223,3.863],"ix":2},"a":{"a":0,"k":[0,0],"ix":1},"s":{"a":0,"k":[100,100],"ix":3},"r":{"a":0,"k":0,"ix":6},"o":{"a":0,"k":100,"ix":7},"sk":{"a":0,"k":0,"ix":4},"sa":{"a":0,"k":0,"ix":5},"nm":"Преобразовать"}],"nm":"Группа 1","np":2,"cix":2,"bm":0,"ix":1,"mn":"ADBE Vector Group","hd":false}],"ip":0,"op":180,"st":0,"bm":0},{"ddd":0,"ind":23,"ty":4,"nm":"Тень","parent":5,"sr":1,"ks":{"o":{"a":0,"k":50,"ix":11},"r":{"a":0,"k":0,"ix":10},"p":{"a":1,"k":[{"i":{"x":0.833,"y":0.833},"o":{"x":0.167,"y":0.167},"t":0,"s":[1.15,180.478,0],"to":[0,0,0],"ti":[0,0,0]},{"t":88,"s":[1.15,180.478,0]}],"ix":2},"a":{"a":0,"k":[48.016,5.19,0],"ix":1},"s":{"a":1,"k":[{"i":{"x":[0.833,0.833,0.833],"y":[0.833,0.833,0.833]},"o":{"x":[0.167,0.167,0.167],"y":[0.167,0.167,0.167]},"t":0,"s":[100,100,100]},{"i":{"x":[0.833,0.833,0.833],"y":[0.833,0.833,0.833]},"o":{"x":[0.167,0.167,0.167],"y":[0.167,0.167,0.167]},"t":88,"s":[78,78,100]},{"t":179,"s":[100,100,100]}],"ix":6}},"ao":0,"shapes":[{"ty":"gr","it":[{"ind":0,"ty":"sh","ix":1,"ks":{"a":0,"k":{"i":[[0,-2.729],[26.38,0],[0,2.729],[-12.005,0]],"o":[[0,2.729],[-26.38,0],[0,-2.729],[12.005,0]],"v":[[47.766,0],[-0.001,4.94],[-47.766,0],[-0.001,-4.94]],"c":true},"ix":2},"nm":"Контур 1","mn":"ADBE Vector Shape - Group","hd":false},{"ty":"fl","c":{"a":0,"k":[0,0,0,1],"ix":4},"o":{"a":0,"k":100,"ix":5},"r":1,"bm":0,"nm":"Заливка 1","mn":"ADBE Vector Graphic - Fill","hd":false},{"ty":"tr","p":{"a":0,"k":[48.015,5.19],"ix":2},"a":{"a":0,"k":[0,0],"ix":1},"s":{"a":0,"k":[100,100],"ix":3},"r":{"a":0,"k":0,"ix":6},"o":{"a":0,"k":100,"ix":7},"sk":{"a":0,"k":0,"ix":4},"sa":{"a":0,"k":0,"ix":5},"nm":"Преобразовать"}],"nm":"Группа 1","np":2,"cix":2,"bm":0,"ix":1,"mn":"ADBE Vector Group","hd":false}],"ip":0,"op":180,"st":0,"bm":0},{"ddd":0,"ind":24,"ty":4,"nm":"Петли","parent":30,"sr":1,"ks":{"o":{"a":0,"k":100,"ix":11},"r":{"a":0,"k":0,"ix":10},"p":{"a":0,"k":[99.218,258.116,0],"ix":2},"a":{"a":0,"k":[14.007,10.648,0],"ix":1},"s":{"a":0,"k":[100,100,100],"ix":6}},"ao":0,"shapes":[{"ty":"gr","it":[{"ind":0,"ty":"sh","ix":1,"ks":{"a":0,"k":{"i":[[0,0],[-3.161,-3.616]],"o":[[3.61,-2.452],[0,0]],"v":[[-6.507,0.82],[6.507,1.808]],"c":false},"ix":2},"nm":"Контур 1","mn":"ADBE Vector Shape - Group","hd":false},{"ty":"st","c":{"a":0,"k":[0.071000005685,0.149000010771,0.136999990426,1],"ix":3},"o":{"a":0,"k":100,"ix":4},"w":{"a":0,"k":3,"ix":5},"lc":2,"lj":1,"ml":10,"bm":0,"nm":"Обводка 1","mn":"ADBE Vector Graphic - Stroke","hd":false},{"ty":"tr","p":{"a":0,"k":[14.007,11.989],"ix":2},"a":{"a":0,"k":[0,0],"ix":1},"s":{"a":0,"k":[100,100],"ix":3},"r":{"a":0,"k":0,"ix":6},"o":{"a":0,"k":100,"ix":7},"sk":{"a":0,"k":0,"ix":4},"sa":{"a":0,"k":0,"ix":5},"nm":"Преобразовать"}],"nm":"Группа 1","np":2,"cix":2,"bm":0,"ix":1,"mn":"ADBE Vector Group","hd":false},{"ty":"gr","it":[{"ind":0,"ty":"sh","ix":1,"ks":{"a":0,"k":{"i":[[0,0],[1.113,-2.622]],"o":[[-1.636,-3.761],[0,0]],"v":[[6.507,1.88],[-6.507,1.88]],"c":false},"ix":2},"nm":"Контур 1","mn":"ADBE Vector Shape - Group","hd":false},{"ty":"st","c":{"a":0,"k":[0.071000005685,0.149000010771,0.136999990426,1],"ix":3},"o":{"a":0,"k":100,"ix":4},"w":{"a":0,"k":3,"ix":5},"lc":2,"lj":1,"ml":10,"bm":0,"nm":"Обводка 1","mn":"ADBE Vector Graphic - Stroke","hd":false},{"ty":"tr","p":{"a":0,"k":[14.007,9.381],"ix":2},"a":{"a":0,"k":[0,0],"ix":1},"s":{"a":0,"k":[100,100],"ix":3},"r":{"a":0,"k":0,"ix":6},"o":{"a":0,"k":100,"ix":7},"sk":{"a":0,"k":0,"ix":4},"sa":{"a":0,"k":0,"ix":5},"nm":"Преобразовать"}],"nm":"Группа 2","np":2,"cix":2,"bm":0,"ix":2,"mn":"ADBE Vector Group","hd":false}],"ip":0,"op":180,"st":0,"bm":0},{"ddd":0,"ind":25,"ty":4,"nm":"Нить","parent":30,"sr":1,"ks":{"o":{"a":0,"k":100,"ix":11},"r":{"a":1,"k":[{"i":{"x":[0.667],"y":[1]},"o":{"x":[0.333],"y":[0]},"t":0,"s":[0]},{"i":{"x":[0.667],"y":[1]},"o":{"x":[0.333],"y":[0]},"t":95,"s":[14]},{"t":179,"s":[0]}],"ix":10},"p":{"a":0,"k":[106.597,259.239,0],"ix":2},"a":{"a":0,"k":[8.372,8.01,0],"ix":1},"s":{"a":0,"k":[100,100,100],"ix":6}},"ao":0,"shapes":[{"ty":"gr","it":[{"ind":0,"ty":"sh","ix":1,"ks":{"a":0,"k":{"i":[[0,0],[128.619,-52.021]],"o":[[31.951,35.945],[0,0]],"v":[[-84.372,-26.01],[-44.247,26.01]],"c":false},"ix":2},"nm":"Контур 1","mn":"ADBE Vector Shape - Group","hd":false},{"ty":"st","c":{"a":0,"k":[0.071000005685,0.149000010771,0.136999990426,1],"ix":3},"o":{"a":0,"k":100,"ix":4},"w":{"a":0,"k":3,"ix":5},"lc":2,"lj":1,"ml":10,"bm":0,"nm":"Обводка 1","mn":"ADBE Vector Graphic - Stroke","hd":false},{"ty":"tr","p":{"a":0,"k":[91.873,33.511],"ix":2},"a":{"a":0,"k":[0,0],"ix":1},"s":{"a":0,"k":[100,100],"ix":3},"r":{"a":0,"k":0,"ix":6},"o":{"a":0,"k":100,"ix":7},"sk":{"a":0,"k":0,"ix":4},"sa":{"a":0,"k":0,"ix":5},"nm":"Преобразовать"}],"nm":"Группа 1","np":2,"cix":2,"bm":0,"ix":1,"mn":"ADBE Vector Group","hd":false}],"ip":0,"op":180,"st":0,"bm":0},{"ddd":0,"ind":26,"ty":4,"nm":"Глаз","parent":30,"sr":1,"ks":{"o":{"a":0,"k":100,"ix":11},"r":{"a":0,"k":0,"ix":10},"p":{"a":0,"k":[134.056,152.618,0],"ix":2},"a":{"a":0,"k":[18.906,18.848,0],"ix":1},"s":{"a":0,"k":[100,100,100],"ix":6}},"ao":0,"shapes":[{"ty":"gr","it":[{"ind":0,"ty":"sh","ix":1,"ks":{"a":0,"k":{"i":[[0,6.274],[6.274,0],[0,-6.275],[-6.276,0]],"o":[[0,-6.275],[-6.276,0],[0,6.274],[6.274,0]],"v":[[11.362,0],[0.001,-11.362],[-11.362,0],[0.001,11.362]],"c":true},"ix":2},"nm":"Контур 1","mn":"ADBE Vector Shape - Group","hd":false},{"ty":"fl","c":{"a":0,"k":[0.097999999102,0.211999990426,0.187999994615,1],"ix":4},"o":{"a":0,"k":100,"ix":5},"r":1,"bm":0,"nm":"Заливка 1","mn":"ADBE Vector Graphic - Fill","hd":false},{"ty":"tr","p":{"a":0,"k":[19.338,20.735],"ix":2},"a":{"a":0,"k":[0,0],"ix":1},"s":{"a":0,"k":[100,100],"ix":3},"r":{"a":0,"k":0,"ix":6},"o":{"a":0,"k":100,"ix":7},"sk":{"a":0,"k":0,"ix":4},"sa":{"a":0,"k":0,"ix":5},"nm":"Преобразовать"}],"nm":"Группа 1","np":2,"cix":2,"bm":0,"ix":1,"mn":"ADBE Vector Group","hd":false},{"ty":"gr","it":[{"ind":0,"ty":"sh","ix":1,"ks":{"a":0,"k":{"i":[[0,0.564],[-12.086,0.898],[-2.315,-7.671],[9.764,0],[0,-10.303],[-0.517,-1.672]],"o":[[0,-10.303],[10.042,-0.747],[-0.812,-9.554],[-10.303,0],[0,1.959],[-0.045,-0.541]],"v":[[-17.896,10.4],[0.371,-9.183],[18.616,5.005],[0.04,-12.054],[-18.616,6.601],[-17.819,12.054]],"c":true},"ix":2},"nm":"Контур 1","mn":"ADBE Vector Shape - Group","hd":false},{"ty":"fl","c":{"a":0,"k":[0.654999976065,0.838999968884,0.8,1],"ix":4},"o":{"a":0,"k":100,"ix":5},"r":1,"bm":0,"nm":"Заливка 1","mn":"ADBE Vector Graphic - Fill","hd":false},{"ty":"tr","p":{"a":0,"k":[18.906,12.304],"ix":2},"a":{"a":0,"k":[0,0],"ix":1},"s":{"a":0,"k":[100,100],"ix":3},"r":{"a":0,"k":0,"ix":6},"o":{"a":0,"k":100,"ix":7},"sk":{"a":0,"k":0,"ix":4},"sa":{"a":0,"k":0,"ix":5},"nm":"Преобразовать"}],"nm":"Группа 2","np":2,"cix":2,"bm":0,"ix":2,"mn":"ADBE Vector Group","hd":false},{"ty":"gr","it":[{"ind":0,"ty":"sh","ix":1,"ks":{"a":0,"k":{"i":[[0,10.303],[10.303,0],[0,-10.303],[-10.303,0]],"o":[[0,-10.303],[-10.303,0],[0,10.303],[10.303,0]],"v":[[18.656,0.866],[0,-17.789],[-18.656,0.866],[0,17.789]],"c":true},"ix":2},"nm":"Контур 1","mn":"ADBE Vector Shape - Group","hd":false},{"ty":"fl","c":{"a":0,"k":[0.902000038297,1,0.980000035903,1],"ix":4},"o":{"a":0,"k":100,"ix":5},"r":1,"bm":0,"nm":"Заливка 1","mn":"ADBE Vector Graphic - Fill","hd":false},{"ty":"tr","p":{"a":0,"k":[18.905,18.039],"ix":2},"a":{"a":0,"k":[0,0],"ix":1},"s":{"a":0,"k":[100,100],"ix":3},"r":{"a":0,"k":0,"ix":6},"o":{"a":0,"k":100,"ix":7},"sk":{"a":0,"k":0,"ix":4},"sa":{"a":0,"k":0,"ix":5},"nm":"Преобразовать"}],"nm":"Группа 3","np":2,"cix":2,"bm":0,"ix":3,"mn":"ADBE Vector Group","hd":false},{"ty":"gr","it":[{"ind":0,"ty":"sh","ix":1,"ks":{"a":0,"k":{"i":[[0,10.303],[10.303,0],[0,-10.303],[-10.303,0]],"o":[[0,-10.303],[-10.303,0],[0,10.303],[10.303,0]],"v":[[18.656,0.867],[0,-17.789],[-18.656,0.867],[0,17.789]],"c":true},"ix":2},"nm":"Контур 1","mn":"ADBE Vector Shape - Group","hd":false},{"ty":"fl","c":{"a":0,"k":[0.541000007181,0.948999980852,0.866999966491,1],"ix":4},"o":{"a":0,"k":100,"ix":5},"r":1,"bm":0,"nm":"Заливка 1","mn":"ADBE Vector Graphic - Fill","hd":false},{"ty":"tr","p":{"a":0,"k":[18.905,19.656],"ix":2},"a":{"a":0,"k":[0,0],"ix":1},"s":{"a":0,"k":[100,100],"ix":3},"r":{"a":0,"k":0,"ix":6},"o":{"a":0,"k":100,"ix":7},"sk":{"a":0,"k":0,"ix":4},"sa":{"a":0,"k":0,"ix":5},"nm":"Преобразовать"}],"nm":"Группа 4","np":2,"cix":2,"bm":0,"ix":4,"mn":"ADBE Vector Group","hd":false}],"ip":0,"op":180,"st":0,"bm":0},{"ddd":0,"ind":27,"ty":4,"nm":"Глаз","parent":30,"sr":1,"ks":{"o":{"a":0,"k":100,"ix":11},"r":{"a":0,"k":0,"ix":10},"p":{"a":0,"k":[74.056,152.643,0],"ix":2},"a":{"a":0,"k":[18.906,18.873,0],"ix":1},"s":{"a":0,"k":[100,100,100],"ix":6}},"ao":0,"shapes":[{"ty":"gr","it":[{"ind":0,"ty":"sh","ix":1,"ks":{"a":0,"k":{"i":[[0,6.274],[6.275,0],[0,-6.275],[-6.275,0]],"o":[[0,-6.275],[-6.275,0],[0,6.274],[6.275,0]],"v":[[11.362,0],[-0.001,-11.362],[-11.362,0],[-0.001,11.362]],"c":true},"ix":2},"nm":"Контур 1","mn":"ADBE Vector Shape - Group","hd":false},{"ty":"fl","c":{"a":0,"k":[0.097999999102,0.211999990426,0.187999994615,1],"ix":4},"o":{"a":0,"k":100,"ix":5},"r":1,"bm":0,"nm":"Заливка 1","mn":"ADBE Vector Graphic - Fill","hd":false},{"ty":"tr","p":{"a":0,"k":[20.713,20.735],"ix":2},"a":{"a":0,"k":[0,0],"ix":1},"s":{"a":0,"k":[100,100],"ix":3},"r":{"a":0,"k":0,"ix":6},"o":{"a":0,"k":100,"ix":7},"sk":{"a":0,"k":0,"ix":4},"sa":{"a":0,"k":0,"ix":5},"nm":"Преобразовать"}],"nm":"Группа 1","np":2,"cix":2,"bm":0,"ix":1,"mn":"ADBE Vector Group","hd":false},{"ty":"gr","it":[{"ind":0,"ty":"sh","ix":1,"ks":{"a":0,"k":{"i":[[0,0.564],[-12.085,0.898],[-2.315,-7.671],[9.764,0],[0,-10.303],[-0.517,-1.672]],"o":[[0,-10.303],[10.043,-0.747],[-0.811,-9.554],[-10.304,0],[0,1.959],[-0.045,-0.541]],"v":[[-17.896,10.4],[0.37,-9.183],[18.615,5.005],[0.041,-12.054],[-18.615,6.601],[-17.819,12.054]],"c":true},"ix":2},"nm":"Контур 1","mn":"ADBE Vector Shape - Group","hd":false},{"ty":"fl","c":{"a":0,"k":[0.654999976065,0.838999968884,0.8,1],"ix":4},"o":{"a":0,"k":100,"ix":5},"r":1,"bm":0,"nm":"Заливка 1","mn":"ADBE Vector Graphic - Fill","hd":false},{"ty":"tr","p":{"a":0,"k":[18.905,12.304],"ix":2},"a":{"a":0,"k":[0,0],"ix":1},"s":{"a":0,"k":[100,100],"ix":3},"r":{"a":0,"k":0,"ix":6},"o":{"a":0,"k":100,"ix":7},"sk":{"a":0,"k":0,"ix":4},"sa":{"a":0,"k":0,"ix":5},"nm":"Преобразовать"}],"nm":"Группа 2","np":2,"cix":2,"bm":0,"ix":2,"mn":"ADBE Vector Group","hd":false},{"ty":"gr","it":[{"ind":0,"ty":"sh","ix":1,"ks":{"a":0,"k":{"i":[[0,10.303],[10.303,0],[0,-10.303],[-10.303,0]],"o":[[0,-10.303],[-10.302,0],[0,10.303],[10.304,0]],"v":[[18.656,0.866],[-0.001,-17.789],[-18.656,0.866],[-0.719,17.789]],"c":true},"ix":2},"nm":"Контур 1","mn":"ADBE Vector Shape - Group","hd":false},{"ty":"fl","c":{"a":0,"k":[0.902000038297,1,0.980000035903,1],"ix":4},"o":{"a":0,"k":100,"ix":5},"r":1,"bm":0,"nm":"Заливка 1","mn":"ADBE Vector Graphic - Fill","hd":false},{"ty":"tr","p":{"a":0,"k":[18.906,18.039],"ix":2},"a":{"a":0,"k":[0,0],"ix":1},"s":{"a":0,"k":[100,100],"ix":3},"r":{"a":0,"k":0,"ix":6},"o":{"a":0,"k":100,"ix":7},"sk":{"a":0,"k":0,"ix":4},"sa":{"a":0,"k":0,"ix":5},"nm":"Преобразовать"}],"nm":"Группа 3","np":2,"cix":2,"bm":0,"ix":3,"mn":"ADBE Vector Group","hd":false},{"ty":"gr","it":[{"ind":0,"ty":"sh","ix":1,"ks":{"a":0,"k":{"i":[[0,10.303],[10.303,0],[0,-10.303],[-10.302,0]],"o":[[0,-10.303],[-10.302,0],[0,10.303],[10.303,0]],"v":[[18.656,0.866],[-0.001,-17.789],[-18.656,0.866],[-0.001,17.789]],"c":true},"ix":2},"nm":"Контур 1","mn":"ADBE Vector Shape - Group","hd":false},{"ty":"fl","c":{"a":0,"k":[0.541000007181,0.948999980852,0.866999966491,1],"ix":4},"o":{"a":0,"k":100,"ix":5},"r":1,"bm":0,"nm":"Заливка 1","mn":"ADBE Vector Graphic - Fill","hd":false},{"ty":"tr","p":{"a":0,"k":[18.906,19.706],"ix":2},"a":{"a":0,"k":[0,0],"ix":1},"s":{"a":0,"k":[100,100],"ix":3},"r":{"a":0,"k":0,"ix":6},"o":{"a":0,"k":100,"ix":7},"sk":{"a":0,"k":0,"ix":4},"sa":{"a":0,"k":0,"ix":5},"nm":"Преобразовать"}],"nm":"Группа 4","np":2,"cix":2,"bm":0,"ix":4,"mn":"ADBE Vector Group","hd":false}],"ip":0,"op":180,"st":0,"bm":0},{"ddd":0,"ind":28,"ty":4,"nm":"Слой-фигура 1","parent":30,"sr":1,"ks":{"o":{"a":0,"k":100,"ix":11},"r":{"a":0,"k":0,"ix":10},"p":{"a":0,"k":[-0.03,-0.75,0],"ix":2},"a":{"a":0,"k":[0,0,0],"ix":1},"s":{"a":0,"k":[100,100,100],"ix":6}},"ao":0,"shapes":[{"ty":"gr","it":[{"ind":0,"ty":"sh","ix":1,"ks":{"a":0,"k":{"i":[[0.562,0],[0.68,-0.739],[-0.234,-2.832],[-0.303,-0.961],[11.571,-6.178],[9.372,-11.388],[0,-32.537],[-18.971,-23.496],[-27.042,0],[-19.073,23.622],[0,33.183],[18.291,22.905],[26.011,2.287],[-0.104,0.599],[3.572,1.563]],"o":[[-0.99,0],[-1.113,1.209],[0.085,1.032],[-12.445,0.75],[-12.075,6.447],[-19.425,23.604],[0,33.183],[19.073,23.622],[27.041,0],[18.972,-23.496],[0,-32.455],[-17.75,-22.227],[0.052,-0.611],[0.474,-2.751],[-0.578,-0.253]],"v":[[0.98,-129.585],[-1.61,-128.44],[-2.935,-122.351],[-2.316,-119.31],[-38.485,-108.878],[-70.807,-82],[-100.931,5.059],[-71.511,92.954],[0.001,129.585],[71.511,92.954],[100.931,5.059],[72.567,-80.787],[4.785,-118.732],[5.078,-120.732],[2.697,-129.204]],"c":true},"ix":2},"nm":"Контур 1","mn":"ADBE Vector Shape - Group","hd":false},{"ind":1,"ty":"sh","ix":2,"ks":{"a":0,"k":{"i":[[-1.367,0],[-0.324,-0.142],[-1.44,-2.073],[0,-66.811],[54.637,0],[0,67.669],[-53.679,1.37],[0.166,2.014]],"o":[[0.284,0],[3.594,1.573],[53.292,3.774],[0,67.669],[-54.639,0],[0,-66.811],[-0.608,-0.998],[-0.282,-3.414]],"v":[[0.98,-127.585],[1.895,-127.372],[3.108,-116.859],[98.931,5.059],[0.001,127.585],[-98.931,5.059],[0.665,-117.436],[-0.942,-122.516]],"c":true},"ix":2},"nm":"Контур 2","mn":"ADBE Vector Shape - Group","hd":false},{"ty":"fl","c":{"a":0,"k":[0.20800000359,0.458999992819,0.404000016755,1],"ix":4},"o":{"a":0,"k":100,"ix":5},"r":1,"bm":0,"nm":"Заливка 1","mn":"ADBE Vector Graphic - Fill","hd":false},{"ty":"tr","p":{"a":0,"k":[101.181,129.835],"ix":2},"a":{"a":0,"k":[0,0],"ix":1},"s":{"a":0,"k":[100,100],"ix":3},"r":{"a":0,"k":0,"ix":6},"o":{"a":0,"k":100,"ix":7},"sk":{"a":0,"k":0,"ix":4},"sa":{"a":0,"k":0,"ix":5},"nm":"Преобразовать"}],"nm":"Группа 3","np":3,"cix":2,"bm":0,"ix":1,"mn":"ADBE Vector Group","hd":false}],"ip":0,"op":180,"st":0,"bm":0},{"ddd":0,"ind":29,"ty":4,"nm":"Кривые Path","parent":30,"sr":1,"ks":{"o":{"a":0,"k":100,"ix":11},"r":{"a":0,"k":0,"ix":10},"p":{"a":0,"k":[144.22,250.101,0],"ix":2},"a":{"a":0,"k":[256,256,0],"ix":1},"s":{"a":0,"k":[100,100,100],"ix":6}},"ao":0,"shapes":[{"ty":"gr","it":[{"ind":0,"ty":"sh","ix":1,"ks":{"a":0,"k":{"i":[[2.418,2.233],[1.605,7.447],[0.269,-0.017],[0.409,0.038],[0,-3.201],[0,0],[1.003,-0.335],[0.378,0],[6.921,0],[0.327,-0.02],[3.392,0],[0.523,0.421],[-0.992,2.221],[0,6.534],[0,0],[0.667,-0.142],[3.255,-3.444],[1.265,-2.834],[-1.535,-1.238],[-1.013,0],[-2.039,1.789],[-3.571,0.23],[-0.268,0],[-2.201,-1.384],[-2.018,0],[-0.584,0.195],[0,0.906]],"o":[[-3.486,-3.221],[-0.266,0.063],[-0.416,0.028],[2.558,12.81],[0,0],[0,0.657],[-0.395,0.131],[-3.475,0],[-0.311,0],[-7.266,0.467],[-0.529,0],[-1.617,-1.303],[2.728,-6.114],[0,0],[-0.672,0.085],[-0.101,3.024],[-2.79,2.951],[-1.864,4.173],[0.863,0.694],[2.161,0],[2.356,-2.066],[0.283,-0.018],[3.475,0],[1.772,1.117],[0.603,0],[2.448,-0.816],[0,-2.026]],"v":[[15.437,1.508],[5.354,-13.793],[4.551,-13.667],[3.314,-13.696],[17.602,7.371],[17.602,7.382],[16.156,8.849],[14.999,9.039],[1.585,4.052],[0.63,4.082],[-13.8,12.05],[-15.372,11.446],[-15.911,6.056],[-2.003,-13.826],[-2.003,-14.05],[-4.014,-13.697],[-11.048,-3.333],[-17.738,5.24],[-16.628,13.004],[-13.8,14.05],[-7.839,10.716],[0.758,6.078],[1.583,6.052],[9.535,8.869],[14.999,11.039],[16.788,10.746],[19.602,7.382]],"c":true},"ix":2},"nm":"Контур 1","mn":"ADBE Vector Shape - Group","hd":false},{"ty":"fl","c":{"a":0,"k":[0.20800000359,0.458999992819,0.404000016755,1],"ix":4},"o":{"a":0,"k":100,"ix":5},"r":1,"bm":0,"nm":"Заливка 1","mn":"ADBE Vector Graphic - Fill","hd":false},{"ty":"tr","p":{"a":0,"k":[210.66,276.745],"ix":2},"a":{"a":0,"k":[0,0],"ix":1},"s":{"a":0,"k":[100,100],"ix":3},"r":{"a":0,"k":0,"ix":6},"o":{"a":0,"k":100,"ix":7},"sk":{"a":0,"k":0,"ix":4},"sa":{"a":0,"k":0,"ix":5},"nm":"Преобразовать"}],"nm":"Группа 1","np":2,"cix":2,"bm":0,"ix":1,"mn":"ADBE Vector Group","hd":false}],"ip":0,"op":180,"st":0,"bm":0},{"ddd":0,"ind":30,"ty":4,"nm":"Шар","parent":1,"sr":1,"ks":{"o":{"a":0,"k":100,"ix":11},"r":{"a":0,"k":0,"ix":10},"p":{"a":0,"k":[-108.825,-81.9,0],"ix":2},"a":{"a":0,"k":[101.181,143.404,0],"ix":1},"s":{"a":0,"k":[130,130,100],"ix":6}},"ao":0,"shapes":[{"ty":"gr","it":[{"ind":0,"ty":"sh","ix":1,"ks":{"a":0,"k":{"i":[[0,-67.509],[27.728,-12.794],[-4.314,71.371],[16.965,9.837]],"o":[[0,67.51],[19.686,-13.154],[4.761,-78.798],[28.599,9.447]],"v":[[35.617,-1.618],[-35.617,115.335],[28.337,4.361],[-34.262,-115.335]],"c":true},"ix":2},"nm":"Контур 1","mn":"ADBE Vector Shape - Group","hd":false},{"ty":"fl","c":{"a":0,"k":[0.517999985639,0.889999988032,0.804000016755,1],"ix":4},"o":{"a":0,"k":100,"ix":5},"r":1,"bm":0,"nm":"Заливка 1","mn":"ADBE Vector Graphic - Fill","hd":false},{"ty":"tr","p":{"a":0,"k":[162.382,135.638],"ix":2},"a":{"a":0,"k":[0,0],"ix":1},"s":{"a":0,"k":[100,100],"ix":3},"r":{"a":0,"k":0,"ix":6},"o":{"a":0,"k":100,"ix":7},"sk":{"a":0,"k":0,"ix":4},"sa":{"a":0,"k":0,"ix":5},"nm":"Преобразовать"}],"nm":"Группа 1","np":2,"cix":2,"bm":0,"ix":1,"mn":"ADBE Vector Group","hd":false},{"ty":"gr","it":[{"ind":0,"ty":"sh","ix":1,"ks":{"a":0,"k":{"i":[[-30.553,-5.967],[0,67.788],[-55.925,2.162],[-3.5,-87.374]],"o":[[-54.635,0],[0,-67.789],[-38.012,7.35],[3.238,80.83]],"v":[[49.465,122.073],[-49.465,-0.669],[49.308,-122.073],[-35.367,6.463]],"c":true},"ix":2},"nm":"Контур 1","mn":"ADBE Vector Shape - Group","hd":false},{"ty":"fl","c":{"a":0,"k":[0.344999994016,0.74900004069,0.670999983245,1],"ix":4},"o":{"a":0,"k":100,"ix":5},"r":1,"bm":0,"nm":"Заливка 1","mn":"ADBE Vector Graphic - Fill","hd":false},{"ty":"tr","p":{"a":0,"k":[54.336,136.411],"ix":2},"a":{"a":0,"k":[0,0],"ix":1},"s":{"a":0,"k":[100,100],"ix":3},"r":{"a":0,"k":0,"ix":6},"o":{"a":0,"k":100,"ix":7},"sk":{"a":0,"k":0,"ix":4},"sa":{"a":0,"k":0,"ix":5},"nm":"Преобразовать"}],"nm":"Группа 2","np":2,"cix":2,"bm":0,"ix":2,"mn":"ADBE Vector Group","hd":false},{"ty":"gr","it":[{"ind":0,"ty":"sh","ix":1,"ks":{"a":0,"k":{"i":[[55.102,0],[0,68.112],[-19.279,23.426],[-25.884,1.141],[0.117,1.411],[-0.916,0.994],[-0.717,0],[-0.451,-0.197],[0.471,-2.734],[-0.116,-0.712],[-17.783,-22.268],[0,-32.228]],"o":[[-55.102,0],[0,-32.306],[18.744,-22.775],[-0.484,-1.172],[-0.209,-2.541],[0.495,-0.538],[0.423,0],[2.853,1.249],[-0.187,1.081],[26.082,2.028],[18.15,22.728],[0,68.112]],"v":[[0,128.585],[-99.931,5.059],[-70.035,-81.365],[-0.915,-118.382],[-1.939,-122.434],[-0.874,-127.763],[0.979,-128.585],[2.296,-128.288],[4.091,-120.902],[3.797,-117.811],[71.785,-80.163],[99.931,5.059]],"c":true},"ix":2},"nm":"Контур 1","mn":"ADBE Vector Shape - Group","hd":false},{"ty":"fl","c":{"a":0,"k":[0.383999992819,0.830999995213,0.741000007181,1],"ix":4},"o":{"a":0,"k":100,"ix":5},"r":1,"bm":0,"nm":"Заливка 1","mn":"ADBE Vector Graphic - Fill","hd":false},{"ty":"tr","p":{"a":0,"k":[101.182,129.835],"ix":2},"a":{"a":0,"k":[0,0],"ix":1},"s":{"a":0,"k":[100,100],"ix":3},"r":{"a":0,"k":0,"ix":6},"o":{"a":0,"k":100,"ix":7},"sk":{"a":0,"k":0,"ix":4},"sa":{"a":0,"k":0,"ix":5},"nm":"Преобразовать"}],"nm":"Группа 4","np":2,"cix":2,"bm":0,"ix":3,"mn":"ADBE Vector Group","hd":false},{"ty":"gr","it":[{"ind":0,"ty":"sh","ix":1,"ks":{"a":0,"k":{"i":[[0,-6.254],[0,0],[1.003,-0.335],[8.4,-0.539],[3.871,3.116],[-0.992,2.22],[-3.505,0.151]],"o":[[0,0],[0,0.657],[-4.184,1.39],[-8.399,0.539],[-1.617,-1.305],[4.151,-4.109],[5.143,-0.227]],"v":[[17.295,-0.469],[17.295,-0.458],[15.851,1.009],[0.323,-3.758],[-15.678,3.607],[-16.217,-1.784],[-5.937,-4.162]],"c":true},"ix":2},"nm":"Контур 1","mn":"ADBE Vector Shape - Group","hd":false},{"ty":"fl","c":{"a":0,"k":[0.298000021542,0.638999968884,0.573000021542,1],"ix":4},"o":{"a":0,"k":100,"ix":5},"r":1,"bm":0,"nm":"Заливка 1","mn":"ADBE Vector Graphic - Fill","hd":false},{"ty":"tr","p":{"a":0,"k":[98.939,279.835],"ix":2},"a":{"a":0,"k":[0,0],"ix":1},"s":{"a":0,"k":[100,100],"ix":3},"r":{"a":0,"k":0,"ix":6},"o":{"a":0,"k":100,"ix":7},"sk":{"a":0,"k":0,"ix":4},"sa":{"a":0,"k":0,"ix":5},"nm":"Преобразовать"}],"nm":"Группа 5","np":2,"cix":2,"bm":0,"ix":4,"mn":"ADBE Vector Group","hd":false},{"ty":"gr","it":[{"ind":0,"ty":"sh","ix":1,"ks":{"a":0,"k":{"i":[[1.784,0],[0.68,0.547],[-1.288,2.884],[-2.73,2.887],[0,3.44],[-2.122,0],[-0.579,-0.113],[-0.966,-0.086],[0,0],[0,0],[-4.211,-3.89],[0,-1.578],[1.759,-0.587],[0.495,0],[1.718,1.081],[3.761,0],[0.305,-0.019],[2.476,-2.172]],"o":[[-0.779,0],[-1.836,-1.482],[1.195,-2.679],[3.597,-3.806],[0,-3.596],[0.417,0],[0.619,0.121],[0,0],[0,0],[0.343,10.35],[2.314,2.138],[0,0.788],[-0.483,0.161],[-1.731,0],[-2.214,-1.394],[-0.29,0],[-3.911,0.251],[-1.887,1.656]],"v":[[-14.044,16.227],[-16.243,15.403],[-17.068,8.823],[-10.564,0.53],[-3.247,-10.651],[-1.126,-16.226],[0.328,-16.023],[2.684,-15.665],[3.565,-15.586],[3.595,-14.702],[14.514,5.418],[18.357,10.547],[16.229,12.973],[14.755,13.215],[9.824,11.2],[1.341,8.227],[0.449,8.255],[-8.743,13.14]],"c":true},"ix":2},"nm":"Контур 1","mn":"ADBE Vector Shape - Group","hd":false},{"ty":"fl","c":{"a":0,"k":[0.383999992819,0.830999995213,0.741000007181,1],"ix":4},"o":{"a":0,"k":100,"ix":5},"r":1,"bm":0,"nm":"Заливка 1","mn":"ADBE Vector Graphic - Fill","hd":false},{"ty":"tr","p":{"a":0,"k":[98.877,268.819],"ix":2},"a":{"a":0,"k":[0,0],"ix":1},"s":{"a":0,"k":[100,100],"ix":3},"r":{"a":0,"k":0,"ix":6},"o":{"a":0,"k":100,"ix":7},"sk":{"a":0,"k":0,"ix":4},"sa":{"a":0,"k":0,"ix":5},"nm":"Преобразовать"}],"nm":"Группа 7","np":2,"cix":2,"bm":0,"ix":5,"mn":"ADBE Vector Group","hd":false}],"ip":0,"op":180,"st":0,"bm":0}],"tgs":1}